dsrt/__init__.py
dsrt/cli.py
dsrt/definitions.py
dsrt/application/Application.py
dsrt/application/Context.py
dsrt/application/Conversant.py
dsrt/application/Preprocessor.py
dsrt/application/Trainer.py
dsrt/application/__init__.py
dsrt/application/utils.py
dsrt/config/Configuration.py
dsrt/config/ConfigurationLoader.py
dsrt/config/__init__.py
dsrt/config/defaults/BaseConfig.py
dsrt/config/defaults/ConversationConfig.py
dsrt/config/defaults/DataConfig.py
dsrt/config/defaults/ModelConfig.py
dsrt/config/defaults/__init__.py
dsrt/config/validation/ConversationConfigValidator.py
dsrt/config/validation/DataConfigValidator.py
dsrt/config/validation/ModelConfigValidator.py
dsrt/config/validation/__init__.py
dsrt/config/wizard/ConversationWizard.py
dsrt/config/wizard/DataWizard.py
dsrt/config/wizard/ModelWizard.py
dsrt/config/wizard/__init__.py
dsrt/conversation/Conversation.py
dsrt/conversation/__init__.py
dsrt/data/Corpus.py
dsrt/data/Properties.py
dsrt/data/SampleSet.py
dsrt/data/__init__.py
dsrt/data/transform/AdjacencyPairer.py
dsrt/data/transform/EncoderDecoderSplitter.py
dsrt/data/transform/Filter.py
dsrt/data/transform/Padder.py
dsrt/data/transform/Tokenizer.py
dsrt/data/transform/Vectorizer.py
dsrt/data/transform/__init__.py
dsrt/models/Decoder.py
dsrt/models/Encoder.py
dsrt/models/EncoderDecoder.py
dsrt/models/__init__.py
dsrt-0.0.1.dist-info/METADATA
dsrt-0.0.1.dist-info/RECORD
dsrt-0.0.1.dist-info/WHEEL
dsrt-0.0.1.dist-info/entry_points.txt
dsrt-0.0.1.dist-info/top_level.txt
