Metadata-Version: 2.1
Name: dsrt
Version: 0.0.1
Summary: High-level library for building and testing neural dialogue systems
Home-page: https://github.com/sbarham/dsrt
Author: Samuel Barham, Nirat Saini
Author-email: sbarham@terpmail.umd.edu, nirat@cs.umd.edu
License: MIT
Keywords: AI artificial intelligence neural dialogue systems chat chatbot chatterbot nlp nautral language generation human computer interaction conversation
Platform: UNKNOWN
Classifier: Development Status :: 2 - Pre-Alpha
Requires-Python: >=3
Requires-Dist: dsrt
Requires-Dist: h5py
